betterpathlib/__init__.py
betterpathlib/main.py
betterpathlib/utils.py
betterpathlib-0.1.9.dist-info/LICENSE
betterpathlib-0.1.9.dist-info/METADATA
betterpathlib-0.1.9.dist-info/WHEEL
betterpathlib-0.1.9.dist-info/RECORD
