Metadata-Version: 2.1
Name: betterpathlib
Version: 0.1.9
Summary: A Path library that is a compatible extension to Python's built-in pathlib.Path.
Home-page: https://github.com/tsoernes/betterpathlib
License: MIT
Keywords: pathlib,path,filesystem
Author: Torstein Sørnes
Author-email: t.soernes@gmail.com
Requires-Python: >=3.11
Classifier: License :: OSI Approved :: MIT License
Classifier: Operating System :: OS Independent
Classifier: Programming Language :: Python :: 3
Classifier: Programming Language :: Python :: 3.11
Classifier: Programming Language :: Python :: 3.12
Classifier: Programming Language :: Python :: 3.13
Project-URL: Documentation, https://github.com/tsoernes/betterpathlib
Project-URL: Repository, https://github.com/tsoernes/betterpathlib
